fast_pedago/__init__.py
fast_pedago/app.py
fast_pedago/configuration/__init__.py
fast_pedago/configuration/oad_optim_sensitivity_analysis.yml
fast_pedago/configuration/oad_sizing_sensitivity_analysis.yml
fast_pedago/gui/__init__.py
fast_pedago/gui/app_interface.py
fast_pedago/gui/components/__init__.py
fast_pedago/gui/components/app_layout.py
fast_pedago/gui/components/input_widgets.py
fast_pedago/gui/components/inputs_container.py
fast_pedago/gui/components/output_figures_container.py
fast_pedago/gui/components/process_figures_container.py
fast_pedago/gui/components/tutorial_container.py
fast_pedago/gui/resources/__init__.py
fast_pedago/gui/resources/background.jpg
fast_pedago/gui/resources/logo_airbus.png
fast_pedago/gui/resources/logo_fast_oad_main_menu.jpg
fast_pedago/gui/resources/logo_fast_oad_top_layer.jpg
fast_pedago/gui/resources/logo_supaero.png
fast_pedago/gui/resources/tutorial/MDA.png
fast_pedago/gui/resources/tutorial/__init__.py
fast_pedago/gui/resources/tutorial/inputs.gif
fast_pedago/gui/resources/tutorial/launch.gif
fast_pedago/gui/resources/tutorial/n2.gif
fast_pedago/gui/resources/tutorial/outputs.gif
fast_pedago/gui/resources/tutorial/text.py
fast_pedago/notebook/FAST_OAD_app.ipynb
fast_pedago/notebook/__init__.py
fast_pedago/notebook/data/__init__.py
fast_pedago/notebook/data/n2.html
fast_pedago/notebook/data/n2.png
fast_pedago/notebook/data/oad_optim_sensitivity_analysis.yml
fast_pedago/notebook/data/oad_sizing_sensitivity_analysis.yml
fast_pedago/notebook/data/xdsm.html
fast_pedago/notebook/data/xdsm.png
fast_pedago/notebook/workdir/inputs/reference_aircraft_input_file.xml
fast_pedago/notebook/workdir/outputs/reference_aircraft_flight_points.csv
fast_pedago/notebook/workdir/outputs/reference_aircraft_output_file.xml
fast_pedago/plots/__init__.py
fast_pedago/plots/functions/__init__.py
fast_pedago/plots/functions/aircraft_front_view.py
fast_pedago/plots/functions/aircraft_side_view.py
fast_pedago/plots/functions/aircraft_top_view.py
fast_pedago-1.0.3.dist-info/METADATA
fast_pedago-1.0.3.dist-info/WHEEL
fast_pedago-1.0.3.dist-info/entry_points.txt
fast_pedago-1.0.3.dist-info/RECORD
